znth/__init__.py
znth/__main__.py
znth/chain.py
znth/models.py
znth/cli/__init__.py
znth/cli/client.py
znth/cli/default.py
znth/cli/init.py
znth/cli/main.py
znth/cli/project.py
znth/cli/task.py
znth/command/__init__.py
znth/command/client.py
znth/command/common.py
znth/command/database.py
znth/command/node.py
znth/command/project.py
znth/command/task.py
znth/factory/__init__.py
znth/factory/client.py
znth/factory/default.py
znth/factory/init.py
znth/factory/project.py
znth/factory/task.py
znth-0.0.2.dist-info/LICENSE
znth-0.0.2.dist-info/METADATA
znth-0.0.2.dist-info/WHEEL
znth-0.0.2.dist-info/top_level.txt
znth-0.0.2.dist-info/RECORD
