Metadata-Version: 2.1
Name: znth
Version: 0.0.2
Summary: A sample Hello, World! applicaton
Home-page: https://github.com/griend/znth
Author: Cees van de Griend
Author-email: c.vande.griend@gmail.com
License: UNKNOWN
Project-URL: Bug Tracker, https://github.com/griend/znth/issues
Platform: UNKNOWN
Classifier: Development Status :: 2 - Pre-Alpha
Classifier: Programming Language :: Python :: 3
Classifier: License :: OSI Approved :: GNU General Public License v3 or later (GPLv3+)
Classifier: Operating System :: OS Independent
Requires-Python: >=3.6
License-File: LICENSE
Requires-Dist: sqlalchemy (>=1.4.23)
